germanium/__init__.py
germanium/ajax-interceptor.js
germanium/create_locator.py
germanium/driver.py
germanium/germanium-extensions-loaded.js
germanium/germanium-ie8-getComputedStyle.js
germanium/iframe.py
germanium/iframe_selector.py
germanium/is-ajax-running.js
germanium/version.py
germanium/impl/ActionChains.py
germanium/impl/__init__.py
germanium/impl/_alert_exists.py
germanium/impl/_is_displayed_filter.py
germanium/impl/_load_script.py
germanium/impl/_workaround.py
germanium/impl/ensure_list.py
germanium/impl/filter-not-displayed.js
germanium/impl/filter-not-displayed.min.js
germanium/impl/filter_not_displayed.py
germanium/impl/wait.py
germanium/locators/AlertLocator.py
germanium/locators/CompositeLocator.py
germanium/locators/CssLocator.py
germanium/locators/DeferredLocator.py
germanium/locators/FilterLocator.py
germanium/locators/InsideFilterLocator.py
germanium/locators/JsLocator.py
germanium/locators/PositionalFilterLocator.py
germanium/locators/SelectorLocator.py
germanium/locators/StaticElementLocator.py
germanium/locators/TextLocator.py
germanium/locators/WindowLocator.py
germanium/locators/XPathLocator.py
germanium/locators/__init__.py
germanium/locators/inside-filter.js
germanium/locators/inside-filter.min.js
germanium/locators/positional-filter.js
germanium/locators/positional-filter.min.js
germanium/locators/text.js
germanium/locators/text.min.js
germanium/points/Box.py
germanium/points/Point.py
germanium/points/__init__.py
germanium/points/box.js
germanium/points/box.min.js
germanium/selectors/AbstractSelector.py
germanium/selectors/Alert.py
germanium/selectors/AnyOfSelector.py
germanium/selectors/Button.py
germanium/selectors/CheckBox.py
germanium/selectors/Css.py
germanium/selectors/Element.py
germanium/selectors/Image.py
germanium/selectors/Input.py
germanium/selectors/InputFile.py
germanium/selectors/InputText.py
germanium/selectors/JsSelector.py
germanium/selectors/Link.py
germanium/selectors/StaticElement.py
germanium/selectors/Text.py
germanium-2.0.12.dist-info/LICENSE
germanium-2.0.12.dist-info/METADATA
germanium-2.0.12.dist-info/WHEEL
germanium-2.0.12.dist-info/top_level.txt
germanium-2.0.12.dist-info/RECORD
